{
  "lexicon": 1,
  "id": "app.vylet.media.images",
  "description": "A set of images that are included in a Vylet post.",
  "defs": {
    "main": {
      "type": "object",
      "required": ["images"],
      "properties": {
        "images": {
          "type": "array",
          "items": { "type": "ref", "ref": "#image" },
          "maxLength": 10
        }
      }
    },
    "image": {
      "type": "object",
      "required": ["image", "alt"],
      "properties": {
        "image": {
          "type": "blob",
          "accept": ["image/*"],
          "maxSize": 10000000
        },
        "alt": {
          "type": "string",
          "description": "Alt text description of the image, for accessibility."
        },
        "aspectRatio": {
          "type": "ref",
          "ref": "app.vylet.media.defs#aspectRatio"
        }
      }
    },
    "view": {
      "type": "object",
      "required": ["images"],
      "properties": {
        "images": {
          "type": "array",
          "items": { "type": "ref", "ref": "#viewImage" },
          "maxLength": 10
        }
      }
    },
    "viewImage": {
      "type": "object",
      "required": ["thumbnail", "fullsize"],
      "properties": {
        "thumbnail": {
          "type": "string",
          "format": "uri",
          "description": "Fully-qualified URL where a thumbnail of the image can be fetched. For example, CDN location provided by the App View."
        },
        "fullsize": {
          "type": "string",
          "format": "uri",
          "description": "Fully-qualified URL where a large version of the image can be fetched. May or may not be the exact original blob. For example, CDN location provided by the App View."
        },
        "alt": {
          "type": "string",
          "description": "Alt text description of the image, for accessibility."
        },
        "aspectRatio": {
          "type": "ref",
          "ref": "app.vylet.media.defs#aspectRatio"
        }
      }
    }
  }
}
